README.rst
setup.cfg
setup.py
twx/__init__.py
twx/twx.py
twx.egg-info/PKG-INFO
twx.egg-info/SOURCES.txt
twx.egg-info/dependency_links.txt
twx.egg-info/requires.txt
twx.egg-info/top_level.txt
twx/botapi/__init__.py
twx/botapi/botapi.py