Metadata-Version: 1.1
Name: twx
Version: 0.5a4
Summary: Telegram Bot API and MTProto Client and Abstraction Layer
Home-page: https://github.com/datamachine/twx
Author: Vince Castellano, Phillip Lopo
Author-email: surye80@gmail.com, philliplopo@gmail.com
License: UNKNOWN
Download-URL: https://github.com/datamachine/twx/archive/twx-0.5a4.tar.gz
Keywords: datamachine,telex,telegram,bot,api,rpc
Platform: Linux
Platform: Unix
Platform: MacOsX
Platform: Windows
Classifier: Development Status :: 4 - Beta
Classifier: Intended Audience :: Developers
Classifier: License :: OSI Approved :: MIT License
Classifier: Operating System :: OS Independent
Classifier: Programming Language :: Python :: 3 :: Only
Classifier: Programming Language :: Python :: 3.4
Classifier: Topic :: Communications :: Chat
Classifier: Topic :: Communications :: File Sharing
